{
	"name": "CCGRTT1181_CNFT",
	"numInputs": "3",
	"numOutputs": "6",
	"maxLevel": "8",
	"numEdges": "55",
	"reliability": "0.00000000000000000000",
	"size": "0.00000000000000000000",
	"area": "0.00000000000000000000",
	"longest_path": "0",
	"gates": "0",
	"sensitivity_factor": "0.00000000000000000000",
	"sinsitivity_factor_percent": "0.00000000000000000000",
	"sensitive_area": "0.00000000000000000000",
	"sensitive_area_percent": "0.00000000000000000000",
	"hash_code": "",
	"numElementsOfEachType": {
		"and": 12,
		"input": 4,
		"not": 3,
		"or": 11,
		"output": 6
	},
	"numEdgesOfEachType": {
		"and-and": 8,
		"and-or": 15,
		"input-and": 8,
		"input-not": 3,
		"input-output": 1,
		"not-and": 8,
		"or-or": 7,
		"or-output": 5
	}
}