{
	"name": "CCGRTT936_CNFT",
	"numInputs": "3",
	"numOutputs": "4",
	"maxLevel": "9",
	"numEdges": "57",
	"reliability": "0.00000000000000000000",
	"size": "0.00000000000000000000",
	"area": "0.00000000000000000000",
	"longest_path": "0",
	"gates": "0",
	"sensitivity_factor": "0.00000000000000000000",
	"sinsitivity_factor_percent": "0.00000000000000000000",
	"sensitive_area": "0.00000000000000000000",
	"sensitive_area_percent": "0.00000000000000000000",
	"hash_code": "",
	"numElementsOfEachType": {
		"and": 12,
		"input": 3,
		"not": 3,
		"or": 13,
		"output": 4
	},
	"numEdgesOfEachType": {
		"and-and": 8,
		"and-or": 17,
		"input-and": 8,
		"input-not": 3,
		"not-and": 8,
		"or-or": 9,
		"or-output": 4
	}
}